audim/__init__.py
audim/py.typed
audim/aud2sub/__init__.py
audim/aud2sub/core.py
audim/aud2sub/transcribers/__init__.py
audim/aud2sub/transcribers/base.py
audim/aud2sub/transcribers/podcast.py
audim/sub2pod/__init__.py
audim/sub2pod/core.py
audim/sub2pod/effects/__init__.py
audim/sub2pod/effects/highlights.py
audim/sub2pod/effects/transitions.py
audim/sub2pod/elements/__init__.py
audim/sub2pod/elements/header.py
audim/sub2pod/elements/profile.py
audim/sub2pod/elements/text.py
audim/sub2pod/elements/watermark.py
audim/sub2pod/layouts/__init__.py
audim/sub2pod/layouts/base.py
audim/sub2pod/layouts/podcast.py
audim/utils/__init__.py
audim/utils/extract.py
audim/utils/playback.py
audim/utils/subtitle.py
audim/vid2sub/__init__.py
audim-0.0.7.dist-info/licenses/LICENSE
audim-0.0.7.dist-info/licenses/NOTICE
audim-0.0.7.dist-info/METADATA
audim-0.0.7.dist-info/WHEEL
audim-0.0.7.dist-info/top_level.txt
audim-0.0.7.dist-info/RECORD
