Metadata-Version: 2.4
Name: audim
Version: 0.0.7
Summary: An animation and video rendering engine for audio-based and voice-based podcast videos.
Author-email: Atanu Sarkar <mratanusarkar@gmail.com>
Maintainer-email: Atanu Sarkar <mratanusarkar@gmail.com>
License: Apache 2.0 License
Project-URL: Homepage, https://github.com/mratanusarkar/audim
Project-URL: Documentation, https://mratanusarkar.github.io/audim
Project-URL: Repository, https://github.com/mratanusarkar/audim
Project-URL: Bug Tracker, https://github.com/mratanusarkar/audim/issues
Project-URL: Changelog, https://mratanusarkar.github.io/audim/devblog/index.md#changelog
Keywords: podcast,animation,video,audio,engine,transcription,subtitle,generation
Classifier: Development Status :: 3 - Alpha
Classifier: Intended Audience :: Developers
Classifier: Intended Audience :: Education
Classifier: Intended Audience :: End Users/Desktop
Classifier: License :: OSI Approved :: Apache Software License
Classifier: Operating System :: OS Independent
Classifier: Programming Language :: Python :: 3
Classifier: Programming Language :: Python :: 3.10
Classifier: Programming Language :: Python :: 3.11
Classifier: Programming Language :: Python :: 3.12
Classifier: Topic :: Multimedia :: Video
Classifier: Topic :: Multimedia :: Sound/Audio
Classifier: Topic :: Software Development :: Libraries :: Python Modules
Requires-Python: >=3.10
License-File: LICENSE
License-File: NOTICE
Requires-Dist: pysrt>=1.1.2
Requires-Dist: opencv-python>=4.9.0.80
Requires-Dist: numpy==1.26.4
Requires-Dist: moviepy==2.0.0.dev2
Requires-Dist: Pillow>=10.2.0
Requires-Dist: matplotlib>=3.8.0
Requires-Dist: whisperx==3.3.1
Requires-Dist: torch==2.2.0
Requires-Dist: torchaudio==2.2.0
Requires-Dist: pydub==0.25.1
Provides-Extra: dev
Requires-Dist: pip>=24.2; extra == "dev"
Requires-Dist: uv>=0.4.20; extra == "dev"
Requires-Dist: pytest>=8.3.3; extra == "dev"
Requires-Dist: isort>=5.13.2; extra == "dev"
Requires-Dist: black>=24.10.0; extra == "dev"
Requires-Dist: ruff>=0.6.9; extra == "dev"
Provides-Extra: docs
Requires-Dist: mkdocs>=1.6.1; extra == "docs"
Requires-Dist: mkdocstrings>=0.26.1; extra == "docs"
Requires-Dist: mkdocstrings-python>=1.11.1; extra == "docs"
Requires-Dist: mkdocs-material>=9.5.39; extra == "docs"
Requires-Dist: mkdocs-minify-plugin>=0.8.0; extra == "docs"
Requires-Dist: mkdocs-glightbox>=0.4.0; extra == "docs"
Requires-Dist: mkdocs-jupyter>=0.25.0; extra == "docs"
Requires-Dist: jupyter>=1.1.1; extra == "docs"
Dynamic: license-file
